i9_everywhere_client/__init__.py
i9_everywhere_client/cli.py
i9_everywhere_client/i9_everywhere.py
i9_everywhere_client-0.1.0.dist-info/LICENSE
i9_everywhere_client-0.1.0.dist-info/METADATA
i9_everywhere_client-0.1.0.dist-info/WHEEL
i9_everywhere_client-0.1.0.dist-info/entry_points.txt
i9_everywhere_client-0.1.0.dist-info/top_level.txt
i9_everywhere_client-0.1.0.dist-info/RECORD
