Metadata-Version: 2.1
Name: i9-everywhere-client
Version: 0.1.0
Summary: A Python client library and CLI for the I9 Everywhere API
Home-page: https://github.com/adhocteam/i9everywhere-python
Author: Paul Smith
Author-email: paul@adhoc.team
License: MIT
Classifier: Development Status :: 3 - Alpha
Classifier: Intended Audience :: Developers
Classifier: License :: OSI Approved :: MIT License
Classifier: Programming Language :: Python :: 3
Classifier: Programming Language :: Python :: 3.6
Classifier: Programming Language :: Python :: 3.7
Classifier: Programming Language :: Python :: 3.8
Classifier: Programming Language :: Python :: 3.9
License-File: LICENSE
Requires-Dist: click
Requires-Dist: httpx
